react_context/__init__.py
react_context-1.0.0.dist-info/LICENSE
react_context-1.0.0.dist-info/METADATA
react_context-1.0.0.dist-info/WHEEL
react_context-1.0.0.dist-info/top_level.txt
react_context-1.0.0.dist-info/RECORD
