Metadata-Version: 2.1
Name: react-context
Version: 1.0.0
Summary: An API to pass data in the nested functions inspired by React Context
Home-page: https://github.com/alessandro308/react_context
Author: Alessandro Pagiaro
Author-email: alessandropagiaro@gmail.com
License: MIT
License-File: LICENSE
